inventorylib/__init__.py
inventorylib/bulk_discount.py
inventorylib/eoq.py
inventorylib/rop.py
inventorylib/safety_stock.py
inventorylib/total_cost.py
inventorylibx-0.1.0.dist-info/licenses/LICENSE
inventorylibx-0.1.0.dist-info/METADATA
inventorylibx-0.1.0.dist-info/WHEEL
inventorylibx-0.1.0.dist-info/top_level.txt
inventorylibx-0.1.0.dist-info/RECORD
